<?xml version="1.0" encoding="utf-8" ?>
<dwsync>
<file name=".acm" server="C:/Users/dxr183/Documents/Case Western/Math SP/test_server/" local="130305025119194751" remote="130305025110000000" />
<file name="simpleFooter.html" server="C:/Users/dxr183/Documents/Case Western/Math SP/test_server/" local="130305025119914792" remote="130305025110000000" />
<file name=".acm" server="C:/xampp/htdocs/singer_build/" local="130305025119194751" remote="130305025110000000" />
<file name="header.html" server="C:/xampp/htdocs/singer_build/" local="130340371966293534" remote="130340371960000000" />
<file name="simpleFooter.html" server="C:/xampp/htdocs/singer_build/" local="130340368835084439" remote="130340368830000000" />
<file name="header.html" server="C:/xampp/htdocs/mathsp/" local="130378265911712662" remote="130378265910000000" />
<file name="simpleFooter.html" server="C:/xampp/htdocs/mathsp/" local="130378575259356586" remote="130378575250000000" />
<file name=".acm" server="C:/xampp/htdocs/" local="130433408818155626" remote="130433408810000000" />
<file name="header.html" server="C:/xampp/htdocs/" local="130433440320787685" remote="130433440320000000" />
<file name="simpleFooter.html" server="C:/xampp/htdocs/" local="130433408818485645" remote="130433408810000000" />
</dwsync>